sf2utils/__init__.py
sf2utils/bag.py
sf2utils/generator.py
sf2utils/instrument.py
sf2utils/modulator.py
sf2utils/preset.py
sf2utils/riffparser.py
sf2utils/sample.py
sf2utils/sf2parse.py
sf2utils/tests/__init__.py
sf2utils/tests/test_parse.py
sf2utils13-1.0.1.dist-info/licenses/AUTHORS
sf2utils13-1.0.1.dist-info/licenses/LICENSE.txt
sf2utils13-1.0.1.dist-info/METADATA
sf2utils13-1.0.1.dist-info/WHEEL
sf2utils13-1.0.1.dist-info/entry_points.txt
sf2utils13-1.0.1.dist-info/top_level.txt
sf2utils13-1.0.1.dist-info/RECORD
