Metadata-Version: 2.4
Name: sf2utils13
Version: 1.0.1
Summary: Sound font 2 parsing library and utilities
Author-email: Olivier Jolly <olivier@pcedev.com>
License: GPLv3+
Project-URL: Homepage, https://gitlab.com/zeograd/sf2utils
Project-URL: Bug tracker, https://gitlab.com/zeograd/sf2utils/-/issues
Keywords: soundfont sf2 sound font
Classifier: Development Status :: 5 - Production/Stable
Classifier: Environment :: Console
Classifier: Intended Audience :: Developers
Classifier: Intended Audience :: End Users/Desktop
Classifier: Topic :: Multimedia :: Sound/Audio
Classifier: Topic :: Software Development :: Libraries :: Python Modules
Classifier: License :: OSI Approved :: GNU Lesser General Public License v3 or later (LGPLv3+)
Classifier: Programming Language :: Python :: 3
Classifier: Programming Language :: Python :: 3.10
Classifier: Programming Language :: Python :: 3.11
Classifier: Programming Language :: Python :: 3.12
Classifier: Programming Language :: Python :: 3.13
Classifier: Operating System :: OS Independent
Requires-Python: >=3.10
License-File: LICENSE.txt
License-File: AUTHORS
Dynamic: license-file
